[{"h":"en-GB","u":"https://pro-bolt.com/clearance-aluminium/","x":1},{"h":"en-AU","u":"https://probolt-australia.com/clearance-aluminium/"},{"h":"en-EU","u":"https://probolt-eu.com/clearance-aluminium/"},{"h":"en-AT","u":"https://probolt-eu.com/clearance-aluminium/"},{"h":"en-BE","u":"https://probolt-eu.com/clearance-aluminium/"},{"h":"en-BG","u":"https://probolt-eu.com/clearance-aluminium/"},{"h":"en-HR","u":"https://probolt-eu.com/clearance-aluminium/"},{"h":"en-CY","u":"https://probolt-eu.com/clearance-aluminium/"},{"h":"en-CZ","u":"https://probolt-eu.com/clearance-aluminium/"},{"h":"en-DK","u":"https://probolt-eu.com/clearance-aluminium/"},{"h":"en-EE","u":"https://probolt-eu.com/clearance-aluminium/"},{"h":"en-FI","u":"https://probolt-eu.com/clearance-aluminium/"},{"h":"en-GR","u":"https://probolt-eu.com/clearance-aluminium/"},{"h":"en-HU","u":"https://probolt-eu.com/clearance-aluminium/"},{"h":"en-IE","u":"https://probolt-eu.com/clearance-aluminium/"},{"h":"en-LV","u":"https://probolt-eu.com/clearance-aluminium/"},{"h":"en-LT","u":"https://probolt-eu.com/clearance-aluminium/"},{"h":"en-LU","u":"https://probolt-eu.com/clearance-aluminium/"},{"h":"en-MT","u":"https://probolt-eu.com/clearance-aluminium/"},{"h":"en-NL","u":"https://probolt-eu.com/clearance-aluminium/"},{"h":"en-PL","u":"https://probolt-eu.com/clearance-aluminium/"},{"h":"en-PT","u":"https://probolt-eu.com/clearance-aluminium/"},{"h":"en-RO","u":"https://probolt-eu.com/clearance-aluminium/"},{"h":"en-SK","u":"https://probolt-eu.com/clearance-aluminium/"},{"h":"en-SI","u":"https://probolt-eu.com/clearance-aluminium/"},{"h":"en-ES","u":"https://probolt-eu.com/clearance-aluminium/"},{"h":"en-SE","u":"https://probolt-eu.com/clearance-aluminium/"},{"h":"de-CH","u":"https://pro-bolt.ch/clearance-aluminium/"},{"h":"ja-JP","u":"https://probolt-japan.com/clearance-aluminium/"},{"h":"en-US","u":"https://probolt-usa.com/clearance-aluminum/"}]