[{"h":"en-GB","u":"https://pro-bolt.com/b2b-titanium-bleed-nipples/","x":1},{"h":"en-AU","u":"https://probolt-australia.com/b2b-titanium-bleed-nipples/"},{"h":"en-EU","u":"https://probolt-eu.com/b2b-titanium-bleed-nipples/"},{"h":"en-AT","u":"https://probolt-eu.com/b2b-titanium-bleed-nipples/"},{"h":"en-BE","u":"https://probolt-eu.com/b2b-titanium-bleed-nipples/"},{"h":"en-BG","u":"https://probolt-eu.com/b2b-titanium-bleed-nipples/"},{"h":"en-HR","u":"https://probolt-eu.com/b2b-titanium-bleed-nipples/"},{"h":"en-CY","u":"https://probolt-eu.com/b2b-titanium-bleed-nipples/"},{"h":"en-CZ","u":"https://probolt-eu.com/b2b-titanium-bleed-nipples/"},{"h":"en-DK","u":"https://probolt-eu.com/b2b-titanium-bleed-nipples/"},{"h":"en-EE","u":"https://probolt-eu.com/b2b-titanium-bleed-nipples/"},{"h":"en-FI","u":"https://probolt-eu.com/b2b-titanium-bleed-nipples/"},{"h":"en-GR","u":"https://probolt-eu.com/b2b-titanium-bleed-nipples/"},{"h":"en-HU","u":"https://probolt-eu.com/b2b-titanium-bleed-nipples/"},{"h":"en-IE","u":"https://probolt-eu.com/b2b-titanium-bleed-nipples/"},{"h":"en-LV","u":"https://probolt-eu.com/b2b-titanium-bleed-nipples/"},{"h":"en-LT","u":"https://probolt-eu.com/b2b-titanium-bleed-nipples/"},{"h":"en-LU","u":"https://probolt-eu.com/b2b-titanium-bleed-nipples/"},{"h":"en-MT","u":"https://probolt-eu.com/b2b-titanium-bleed-nipples/"},{"h":"en-NL","u":"https://probolt-eu.com/b2b-titanium-bleed-nipples/"},{"h":"en-PL","u":"https://probolt-eu.com/b2b-titanium-bleed-nipples/"},{"h":"en-PT","u":"https://probolt-eu.com/b2b-titanium-bleed-nipples/"},{"h":"en-RO","u":"https://probolt-eu.com/b2b-titanium-bleed-nipples/"},{"h":"en-SK","u":"https://probolt-eu.com/b2b-titanium-bleed-nipples/"},{"h":"en-SI","u":"https://probolt-eu.com/b2b-titanium-bleed-nipples/"},{"h":"en-ES","u":"https://probolt-eu.com/b2b-titanium-bleed-nipples/"},{"h":"en-SE","u":"https://probolt-eu.com/b2b-titanium-bleed-nipples/"},{"h":"de-CH","u":"https://pro-bolt.ch/b2b-titanium-bleed-nipples/"},{"h":"ja-JP","u":"https://probolt-japan.com/b2b-titanium-bleed-nipples/"},{"h":"en-US","u":"https://probolt-usa.com/b2b-titanium-bleed-nipples/"}]